.project
.pydevproject
CHANGES.txt
Contributors.txt
MANIFEST.in
README.txt
paster.ini
setup.cfg
setup.py
.settings/org.eclipse.core.resources.prefs
docs/.buildinfo
docs/conf.py
docs/index.rst
tests/__init__.py
tests/test_widget.py
tw/__init__.py
tw.jqmultiselect.egg-info/PKG-INFO
tw.jqmultiselect.egg-info/SOURCES.txt
tw.jqmultiselect.egg-info/dependency_links.txt
tw.jqmultiselect.egg-info/entry_points.txt
tw.jqmultiselect.egg-info/namespace_packages.txt
tw.jqmultiselect.egg-info/not-zip-safe
tw.jqmultiselect.egg-info/paster_plugins.txt
tw.jqmultiselect.egg-info/requires.txt
tw.jqmultiselect.egg-info/top_level.txt
tw/jqmultiselect/__init__.py
tw/jqmultiselect/release.py
tw/jqmultiselect/samples.py
tw/jqmultiselect/widgets.py
tw/jqmultiselect/static/css/ui.multiselect.css
tw/jqmultiselect/static/js/ui.multiselect.js
tw/jqmultiselect/templates/__init__.py