Metadata-Version: 1.0
Name: tw.jqmultiselect
Version: 0.2
Summary: multiselection widget
Home-page: http://code.google.com/p/jqmultiselect/
Author: Nicolas Laurance
Author-email: nicolas.laurance@gmail.com
License: UNKNOWN
Keywords: toscawidgets.widgets,multiselect,form
Platform: UNKNOWN
Classifier: Development Status :: 3 - Alpha
Classifier: Environment :: Web Environment
Classifier: Environment :: Web Environment :: ToscaWidgets
Classifier: Topic :: Software Development :: Libraries :: Python Modules
Classifier: Topic :: Software Development :: Widget Sets
Classifier: Intended Audience :: Developers
Classifier: Operating System :: OS Independent
Classifier: Programming Language :: Python
Classifier: Framework :: TurboGears :: Widgets
Classifier: License :: OSI Approved :: GNU Affero General Public License v3
Classifier: License :: OSI Approved :: MIT License
